{"properties":{"type":{"type":"string","enum":["reasoning"],"description":"The type of the item. Always `reasoning`.","default":"reasoning"},"id":{"type":"string","description":"The unique ID of the reasoning item."},"content":{"items":{"oneOf":[{"properties":{"type":{"type":"string","enum":["input_text"],"description":"The type of the input item. Always `input_text`.","default":"input_text"},"text":{"type":"string","description":"The text input to the model."}},"type":"object","required":["type","text"],"title":"Input text","description":"A text input to the model.","x-readme-ref-name":"InputTextContent"},{"properties":{"type":{"type":"string","enum":["output_text"],"description":"The type of the output text. Always `output_text`.","default":"output_text"},"text":{"type":"string","description":"The text output from the model."},"annotations":{"items":{"oneOf":[{"properties":{"type":{"type":"string","enum":["url_citation"],"description":"The type of the URL citation. Always `url_citation`.","default":"url_citation"},"url":{"type":"string","description":"The URL of the web resource."},"start_index":{"type":"integer","description":"The index of the first character of the URL citation in the message."},"end_index":{"type":"integer","description":"The index of the last character of the URL citation in the message."},"title":{"type":"string","description":"The title of the web resource."}},"type":"object","required":["type","url","start_index","end_index","title"],"title":"URL citation","description":"A citation for a web resource used to generate a model response.","x-readme-ref-name":"UrlCitationBody"}],"description":"An annotation that applies to a span of output text.","discriminator":{"propertyName":"type"},"x-readme-ref-name":"Annotation"},"type":"array","description":"The annotations of the text output."},"logprobs":{"items":{"properties":{"token":{"type":"string"},"logprob":{"type":"number"},"bytes":{"items":{"type":"integer"},"type":"array"},"top_logprobs":{"items":{"properties":{"token":{"type":"string"},"logprob":{"type":"number"},"bytes":{"items":{"type":"integer"},"type":"array"}},"type":"object","required":["token","logprob","bytes"],"title":"Top log probability","description":"The top log probability of a token.","x-readme-ref-name":"TopLogProb"},"type":"array"}},"type":"object","required":["token","logprob","bytes","top_logprobs"],"title":"Log probability","description":"The log probability of a token.","x-readme-ref-name":"LogProb"},"type":"array"}},"type":"object","required":["type","text","annotations","logprobs"],"title":"Output text","description":"A text output from the model.","x-readme-ref-name":"OutputTextContent"},{"properties":{"type":{"type":"string","enum":["text"],"default":"text"},"text":{"type":"string"}},"type":"object","required":["type","text"],"title":"Text Content","description":"A text content.","x-readme-ref-name":"TextContent"},{"properties":{"type":{"type":"string","enum":["summary_text"],"description":"The type of the object. Always `summary_text`.","default":"summary_text"},"text":{"type":"string","description":"A summary of the reasoning output from the model so far."}},"type":"object","required":["type","text"],"title":"Summary text","description":"A summary text from the model.","x-readme-ref-name":"SummaryTextContent"},{"properties":{"type":{"type":"string","enum":["reasoning_text"],"description":"The type of the reasoning text. Always `reasoning_text`.","default":"reasoning_text"},"text":{"type":"string","description":"The reasoning text from the model."}},"type":"object","required":["type","text"],"title":"Reasoning text","description":"Reasoning text from the model.","x-readme-ref-name":"ReasoningTextContent"},{"properties":{"type":{"type":"string","enum":["refusal"],"description":"The type of the refusal. Always `refusal`.","default":"refusal"},"refusal":{"type":"string","description":"The refusal explanation from the model."}},"type":"object","required":["type","refusal"],"title":"Refusal","description":"A refusal from the model.","x-readme-ref-name":"RefusalContent"},{"properties":{"type":{"type":"string","enum":["input_image"],"description":"The type of the input item. Always `input_image`.","default":"input_image"},"image_url":{"anyOf":[{"type":"string","description":"The URL of the image to be sent to the model. A fully qualified URL or base64 encoded image in a data URL."},{"type":"null"}]},"detail":{"allOf":[{"type":"string","enum":["low","high","auto"],"x-enumDescriptions":{"auto":"Choose the detail level automatically.","high":"Allows the model to \"see\" a higher-resolution version of the image, usually increasing input token costs.","low":"Restricts the model to a lower-resolution version of the image."},"x-readme-ref-name":"ImageDetail"},{"description":"The detail level of the image to be sent to the model. One of `high`, `low`, or `auto`. Defaults to `auto`."}]}},"type":"object","required":["type","image_url","detail"],"title":"Input image","description":"An image input to the model. Learn about [image inputs](/docs/guides/vision).","x-readme-ref-name":"InputImageContent"},{"properties":{"type":{"type":"string","enum":["input_file"],"description":"The type of the input item. Always `input_file`.","default":"input_file"},"filename":{"type":"string","description":"The name of the file to be sent to the model."},"file_url":{"type":"string","description":"The URL of the file to be sent to the model."}},"type":"object","required":["type"],"title":"Input file","description":"A file input to the model.","x-readme-ref-name":"InputFileContent"}],"description":"A content part that makes up an input or output item.","discriminator":{"propertyName":"type"}},"type":"array","description":"The reasoning content that was generated."},"summary":{"items":{"oneOf":[{"properties":{"type":{"type":"string","enum":["input_text"],"description":"The type of the input item. Always `input_text`.","default":"input_text"},"text":{"type":"string","description":"The text input to the model."}},"type":"object","required":["type","text"],"title":"Input text","description":"A text input to the model.","x-readme-ref-name":"InputTextContent"},{"properties":{"type":{"type":"string","enum":["output_text"],"description":"The type of the output text. Always `output_text`.","default":"output_text"},"text":{"type":"string","description":"The text output from the model."},"annotations":{"items":{"oneOf":[{"properties":{"type":{"type":"string","enum":["url_citation"],"description":"The type of the URL citation. Always `url_citation`.","default":"url_citation"},"url":{"type":"string","description":"The URL of the web resource."},"start_index":{"type":"integer","description":"The index of the first character of the URL citation in the message."},"end_index":{"type":"integer","description":"The index of the last character of the URL citation in the message."},"title":{"type":"string","description":"The title of the web resource."}},"type":"object","required":["type","url","start_index","end_index","title"],"title":"URL citation","description":"A citation for a web resource used to generate a model response.","x-readme-ref-name":"UrlCitationBody"}],"description":"An annotation that applies to a span of output text.","discriminator":{"propertyName":"type"},"x-readme-ref-name":"Annotation"},"type":"array","description":"The annotations of the text output."},"logprobs":{"items":{"properties":{"token":{"type":"string"},"logprob":{"type":"number"},"bytes":{"items":{"type":"integer"},"type":"array"},"top_logprobs":{"items":{"properties":{"token":{"type":"string"},"logprob":{"type":"number"},"bytes":{"items":{"type":"integer"},"type":"array"}},"type":"object","required":["token","logprob","bytes"],"title":"Top log probability","description":"The top log probability of a token.","x-readme-ref-name":"TopLogProb"},"type":"array"}},"type":"object","required":["token","logprob","bytes","top_logprobs"],"title":"Log probability","description":"The log probability of a token.","x-readme-ref-name":"LogProb"},"type":"array"}},"type":"object","required":["type","text","annotations","logprobs"],"title":"Output text","description":"A text output from the model.","x-readme-ref-name":"OutputTextContent"},{"properties":{"type":{"type":"string","enum":["text"],"default":"text"},"text":{"type":"string"}},"type":"object","required":["type","text"],"title":"Text Content","description":"A text content.","x-readme-ref-name":"TextContent"},{"properties":{"type":{"type":"string","enum":["summary_text"],"description":"The type of the object. Always `summary_text`.","default":"summary_text"},"text":{"type":"string","description":"A summary of the reasoning output from the model so far."}},"type":"object","required":["type","text"],"title":"Summary text","description":"A summary text from the model.","x-readme-ref-name":"SummaryTextContent"},{"properties":{"type":{"type":"string","enum":["reasoning_text"],"description":"The type of the reasoning text. Always `reasoning_text`.","default":"reasoning_text"},"text":{"type":"string","description":"The reasoning text from the model."}},"type":"object","required":["type","text"],"title":"Reasoning text","description":"Reasoning text from the model.","x-readme-ref-name":"ReasoningTextContent"},{"properties":{"type":{"type":"string","enum":["refusal"],"description":"The type of the refusal. Always `refusal`.","default":"refusal"},"refusal":{"type":"string","description":"The refusal explanation from the model."}},"type":"object","required":["type","refusal"],"title":"Refusal","description":"A refusal from the model.","x-readme-ref-name":"RefusalContent"},{"properties":{"type":{"type":"string","enum":["input_image"],"description":"The type of the input item. Always `input_image`.","default":"input_image"},"image_url":{"anyOf":[{"type":"string","description":"The URL of the image to be sent to the model. A fully qualified URL or base64 encoded image in a data URL."},{"type":"null"}]},"detail":{"allOf":[{"type":"string","enum":["low","high","auto"],"x-enumDescriptions":{"auto":"Choose the detail level automatically.","high":"Allows the model to \"see\" a higher-resolution version of the image, usually increasing input token costs.","low":"Restricts the model to a lower-resolution version of the image."},"x-readme-ref-name":"ImageDetail"},{"description":"The detail level of the image to be sent to the model. One of `high`, `low`, or `auto`. Defaults to `auto`."}]}},"type":"object","required":["type","image_url","detail"],"title":"Input image","description":"An image input to the model. Learn about [image inputs](/docs/guides/vision).","x-readme-ref-name":"InputImageContent"},{"properties":{"type":{"type":"string","enum":["input_file"],"description":"The type of the input item. Always `input_file`.","default":"input_file"},"filename":{"type":"string","description":"The name of the file to be sent to the model."},"file_url":{"type":"string","description":"The URL of the file to be sent to the model."}},"type":"object","required":["type"],"title":"Input file","description":"A file input to the model.","x-readme-ref-name":"InputFileContent"}],"description":"A content part that makes up an input or output item.","discriminator":{"propertyName":"type"}},"type":"array","description":"The reasoning summary content that was generated."},"encrypted_content":{"type":"string","description":"The encrypted reasoning content that was generated."}},"type":"object","required":["type","id","summary"],"title":"Reasoning item","description":"A reasoning item that was generated by the model.","x-readme-ref-name":"ReasoningBody"}